{"seed":873247557,"allCommands":[[{"command":"---------- SUBTASK_ENCODING -------------","agentID":0},{"command":"{<class 'lux_ai.lux_gym.reward_spaces.CollectNWood'>: 0","agentID":0},{"command":" <class 'lux_ai.lux_gym.reward_spaces.CollectNCoal'>: 1","agentID":0},{"command":" <class 'lux_ai.lux_gym.reward_spaces.CollectNUranium'>: 2","agentID":0},{"command":" <class 'lux_ai.lux_gym.reward_spaces.MakeNCityTiles'>: 3","agentID":0},{"command":" <class 'lux_ai.lux_gym.reward_spaces.MakeNContiguousCityTiles'>: 4","agentID":0},{"command":" <class 'lux_ai.lux_gym.reward_spaces.CollectNTotalFuel'>: 5","agentID":0},{"command":" <class 'lux_ai.lux_gym.reward_spaces.SurviveNNights'>: 6","agentID":0},{"command":" <class 'lux_ai.lux_gym.reward_spaces.GetNResearchPoints'>: 7","agentID":0},{"command":" None: 8}","agentID":0},{"command":"----------------------------------------","agentID":0},{"command":"---------- SUBTASK_ENCODING -------------","agentID":1},{"command":"{<class 'lux_ai.lux_gym.reward_spaces.CollectNWood'>: 0","agentID":1},{"command":" <class 'lux_ai.lux_gym.reward_spaces.CollectNCoal'>: 1","agentID":1},{"command":" <class 'lux_ai.lux_gym.reward_spaces.CollectNUranium'>: 2","agentID":1},{"command":" <class 'lux_ai.lux_gym.reward_spaces.MakeNCityTiles'>: 3","agentID":1},{"command":" <class 'lux_ai.lux_gym.reward_spaces.MakeNContiguousCityTiles'>: 4","agentID":1},{"command":" <class 'lux_ai.lux_gym.reward_spaces.CollectNTotalFuel'>: 5","agentID":1},{"command":" <class 'lux_ai.lux_gym.reward_spaces.SurviveNNights'>: 6","agentID":1},{"command":" <class 'lux_ai.lux_gym.reward_spaces.GetNResearchPoints'>: 7","agentID":1},{"command":" None: 8}","agentID":1},{"command":"----------------------------------------","agentID":1}],[],[],[],[],[],[],[],[],[],[],[],[],[],[],[],[],[],[],[],[],[],[],[],[],[],[],[],[],[],[],[],[],[],[],[],[],[],[],[],[],[],[],[],[],[],[],[],[],[],[],[],[],[],[],[],[],[],[],[],[],[],[],[],[],[],[],[],[],[],[],[],[],[],[],[],[],[],[],[],[],[],[],[],[],[],[],[],[],[],[],[],[],[],[],[],[],[],[],[],[],[],[],[],[],[],[],[],[],[],[],[],[],[],[],[],[],[],[],[],[],[],[],[],[],[],[],[],[],[],[],[],[],[],[],[],[],[],[],[],[],[],[],[],[],[],[],[],[],[],[],[],[],[],[],[],[],[],[],[],[],[],[],[],[],[],[],[],[],[],[],[],[],[],[],[],[],[],[],[],[],[],[],[],[],[],[],[],[],[],[],[],[],[],[],[],[],[],[],[],[],[],[],[],[],[],[],[],[],[],[],[],[],[],[],[],[],[],[],[],[],[],[],[],[],[],[],[],[],[],[],[],[],[],[],[],[],[],[],[],[],[],[],[],[],[],[],[],[],[],[],[],[],[],[],[],[],[],[],[],[],[],[],[],[],[],[],[],[],[],[],[],[],[],[],[],[],[],[],[],[],[],[],[],[],[],[],[],[],[],[],[],[],[],[],[],[],[],[],[],[],[],[],[],[],[],[],[],[],[],[],[],[],[],[],[],[],[],[],[],[],[],[],[],[],[],[],[],[],[],[],[],[],[],[],[],[],[],[],[],[],[],[],[],[],[],[],[],[],[],[],[],[],[],[],[],[],[],[],[]],"mapType":"random","width":12,"height":12,"teamDetails":[{"name":"main.py","tournamentID":""},{"name":"main.py","tournamentID":""}],"version":"3.1.0","results":{"ranks":[{"rank":1,"agentID":0},{"rank":1,"agentID":1}],"replayFile":"_main__vs___main/0_12.json"}}